bureaucrate/__init__.py
bureaucrate/__main__.py
bureaucrate/bureaucrate.py
bureaucrate/repl.py
bureaucrate/utils.py
bureaucrate-0.3.8.dist-info/DESCRIPTION.rst
bureaucrate-0.3.8.dist-info/METADATA
bureaucrate-0.3.8.dist-info/RECORD
bureaucrate-0.3.8.dist-info/WHEEL
bureaucrate-0.3.8.dist-info/entry_points.txt
bureaucrate-0.3.8.dist-info/metadata.json
bureaucrate-0.3.8.dist-info/top_level.txt
