Metadata-Version: 2.0
Name: bureaucrate
Version: 0.3.8
Summary: A maildir-based executer of rules, destined to sort and automate mail
Home-page: https://github.com/paulollivier/bureaucrate
Author: Paul Ollivier
Author-email: contact@paulollivier.fr
License: MIT license
Keywords: bureaucrate
Platform: UNKNOWN
Classifier: Development Status :: 4 - Beta
Classifier: Intended Audience :: Developers
Classifier: License :: OSI Approved :: MIT License
Classifier: Natural Language :: English
Classifier: Environment :: Console
Classifier: Topic :: Communications :: Email :: Filters
Classifier: Programming Language :: Python :: 3 :: Only
Classifier: Programming Language :: Python :: 3.5
Classifier: Programming Language :: Python :: 3.6
Requires-Dist: dateutils (==0.6.6)
Requires-Dist: chardet (==3.0.4)
